defisheye/__init__.py
defisheye/__main__.py
defisheye/defisheye.py
defisheye/defisheyeapp.py
defisheye/gui/__init__.py
defisheye/gui/camera.png
defisheye/gui/edit-image.png
defisheye/gui/image200x200.png
defisheye/gui/main.ui
defisheye/gui/open-image.png
defisheye-1.3.0.dist-info/LICENSE-2.0.txt
defisheye-1.3.0.dist-info/METADATA
defisheye-1.3.0.dist-info/WHEEL
defisheye-1.3.0.dist-info/entry_points.txt
defisheye-1.3.0.dist-info/top_level.txt
defisheye-1.3.0.dist-info/RECORD
