Metadata-Version: 2.1
Name: defisheye
Version: 1.3.0
Summary: Fast defisheye algorithm
Home-page: https://github.com/duducosmos/defisheye
Author: Eduardo S. Pereira
Author-email: pereira.somoza@gmail.com
License: Apache License 2.0
Platform: UNKNOWN
License-File: LICENSE-2.0.txt
Requires-Dist: Pillow
Requires-Dist: argcomplete
Requires-Dist: numpy
Requires-Dist: opencv-python
Requires-Dist: pygubu
Requires-Dist: tqdm
